channel/BaseChannel.py
channel/ChannelConsts.py
channel/ModifyChannel.py
channel/ModifyResourceUtils.py
channel/__init__.py
channel/special/OneStoreChannel.py
channel/special/SamsungChannel.py
core/__init__.py
core/build_apk_task.py
core/build_apk_tools.py
core/global_utils.py
packchannel-1.0.2.data/data/README.md
packchannel-1.0.2.data/data/main.py
packchannel-1.0.2.data/data/requirements.txt
utils/__init__.py
utils/aar_utils.py
utils/file_utils.py
utils/log_utils.py
utils/manifest_utils.py
utils/merge_utils.py
utils/notice_utils.py
utils/res_merger.py
utils/res_utils.py
utils/shell_utils.py
utils/smali_utils.py
utils/store_utils.py
packchannel-1.0.2.dist-info/LICENSE
packchannel-1.0.2.dist-info/METADATA
packchannel-1.0.2.dist-info/WHEEL
packchannel-1.0.2.dist-info/entry_points.txt
packchannel-1.0.2.dist-info/top_level.txt
packchannel-1.0.2.dist-info/RECORD
