Metadata-Version: 2.1
Name: packchannel
Version: 1.0.2
Summary: A tool channel test
Home-page: https://github.com/
Author: lining
Author-email: 58633102@qq.com
License: UNKNOWN
Platform: UNKNOWN
Classifier: Programming Language :: Python :: 3
Classifier: License :: OSI Approved :: MIT License
Classifier: Operating System :: OS Independent
Requires-Python: >=3.6
License-File: LICENSE
Requires-Dist: backports.tarfile (==1.2.0)
Requires-Dist: certifi (==2025.4.26)
Requires-Dist: charset-normalizer (==3.4.2)
Requires-Dist: docutils (==0.21.2)
Requires-Dist: id (==1.5.0)
Requires-Dist: idna (==3.10)
Requires-Dist: importlib-metadata (==8.7.0)
Requires-Dist: jaraco.classes (==3.4.0)
Requires-Dist: jaraco.context (==6.0.1)
Requires-Dist: jaraco.functools (==4.1.0)
Requires-Dist: keyring (==25.6.0)
Requires-Dist: lxml (==5.4.0)
Requires-Dist: markdown-it-py (==3.0.0)
Requires-Dist: mdurl (==0.1.2)
Requires-Dist: more-itertools (==10.7.0)
Requires-Dist: nh3 (==0.2.21)
Requires-Dist: packaging (==25.0)
Requires-Dist: packchannel (==1.0.0)
Requires-Dist: pygments (==2.19.1)
Requires-Dist: readme-renderer (==44.0)
Requires-Dist: requests (==2.32.3)
Requires-Dist: requests-toolbelt (==1.0.0)
Requires-Dist: rfc3986 (==2.0.0)
Requires-Dist: rich (==14.0.0)
Requires-Dist: twine (==6.1.0)
Requires-Dist: typing-extensions (==4.13.2)
Requires-Dist: urllib3 (==2.4.0)
Requires-Dist: utils (==1.0.2)
Requires-Dist: zipp (==3.21.0)
